qmsa/__init__.py
qmsa/model.py
qmsa/utils.py
qmsa-0.0.3.dist-info/LICENSE
qmsa-0.0.3.dist-info/METADATA
qmsa-0.0.3.dist-info/WHEEL
qmsa-0.0.3.dist-info/top_level.txt
qmsa-0.0.3.dist-info/RECORD
