Metadata-Version: 2.1
Name: qmsa
Version: 0.0.3
Summary: Quantum Modelling Simulation Analysis is a Python package to improve workflow efficiency in various material realted calculations.
Author-email: Susy Exists <susy@materials.wiki>
Project-URL: Homepage, https://github.com/susyexists/qmsa
Classifier: Programming Language :: Python :: 3
Classifier: License :: OSI Approved :: MIT License
Classifier: Operating System :: OS Independent
Requires-Python: >=3.10
License-File: LICENSE
Requires-Dist: numpy ==1.26.4
